README.md
setup.py
MyRandomForestClassifier/__init__.py
MyRandomForestClassifier/decision_tree.py
MyRandomForestClassifier/random_forest.py
MyRandomForestClassifier.egg-info/PKG-INFO
MyRandomForestClassifier.egg-info/SOURCES.txt
MyRandomForestClassifier.egg-info/dependency_links.txt
MyRandomForestClassifier.egg-info/requires.txt
MyRandomForestClassifier.egg-info/top_level.txt