Metadata-Version: 2.1
Name: MyRandomForestClassifier
Version: 0.1
Summary: A custom implementation of Random Forest Classifier
Home-page: https://github.com/Boobalan-Ashokan/MyRandomForestClassifier
Author: Boobalan-Ashokan
Author-email: balanshai123@email.com
License: MIT
